README.txt
document_it.py
setup.py
document_it.egg-info/PKG-INFO
document_it.egg-info/SOURCES.txt
document_it.egg-info/dependency_links.txt
document_it.egg-info/entry_points.txt
document_it.egg-info/not-zip-safe
document_it.egg-info/requires.txt
document_it.egg-info/top_level.txt