Metadata-Version: 1.0
Name: document-it
Version: 0.1.1
Summary: mirror text documentation to MDN
Home-page: http://k0s.org/mozilla/hg/DocumentIt
Author: Jeff Hammel
Author-email: jhammel@mozilla.com
License: MPL
Keywords: mozilla
Platform: UNKNOWN
